LICENSE
README.md
setup.cfg
setup.py
quantml/__init__.py
quantml/__main__.py
quantml.egg-info/PKG-INFO
quantml.egg-info/SOURCES.txt
quantml.egg-info/dependency_links.txt
quantml.egg-info/entry_points.txt
quantml.egg-info/top_level.txt