Metadata-Version: 2.1
Name: quantml
Version: 0.0.3
Summary: Algorithmic Trading using Machine Learning
Home-page: https://github.com/markgacoka/quantml
Author: Gacoka Mbui, Stevedavies Ndegwa
Author-email: markgacoka@gmail.com, stevedaviesndegwa@gmail.com
License: MIT
Keywords: algorithmic trading,Crypto,Quantitative Finance,trading bot
Platform: UNKNOWN
Classifier: Development Status :: 1 - Planning
Classifier: Framework :: Django
Classifier: Programming Language :: Python :: 3
Classifier: License :: OSI Approved :: MIT License
Classifier: Operating System :: OS Independent
Classifier: Topic :: Scientific/Engineering :: Artificial Intelligence
Requires-Python: >=3.9
License-File: LICENSE
